[
    {
        "id": 2023,
        "name": "Aragatsotn Region",
        "country": "ARM",
        "state": "AG"
    },
    {
        "id": 2024,
        "name": "Ararat Province",
        "country": "ARM",
        "state": "AR"
    },
    {
        "id": 2026,
        "name": "Armavir Region",
        "country": "ARM",
        "state": "AV"
    },
    {
        "id": 2028,
        "name": "Gegharkunik Province",
        "country": "ARM",
        "state": "GR"
    },
    {
        "id": 2033,
        "name": "Kotayk Region",
        "country": "ARM",
        "state": "KT"
    },
    {
        "id": 2029,
        "name": "Lori Region",
        "country": "ARM",
        "state": "LO"
    },
    {
        "id": 2031,
        "name": "Shirak Region",
        "country": "ARM",
        "state": "SH"
    },
    {
        "id": 2027,
        "name": "Syunik Province",
        "country": "ARM",
        "state": "SU"
    },
    {
        "id": 2032,
        "name": "Tavush Region",
        "country": "ARM",
        "state": "TV"
    },
    {
        "id": 2025,
        "name": "Vayots Dzor Region",
        "country": "ARM",
        "state": "VD"
    },
    {
        "id": 2030,
        "name": "Yerevan",
        "country": "ARM",
        "state": "ER"
    }
]