[
    {
        "id": 63239,
        "name": "Amagi",
        "country": "JPN",
        "state": "40"
    },
    {
        "id": 63263,
        "name": "Asakura Shi",
        "country": "JPN",
        "state": "40"
    },
    {
        "id": 63290,
        "name": "Buzen",
        "country": "JPN",
        "state": "40"
    },
    {
        "id": 63291,
        "name": "Buzen-shi",
        "country": "JPN",
        "state": "40"
    },
    {
        "id": 63298,
        "name": "Chikugo Shi",
        "country": "JPN",
        "state": "40"
    },
    {
        "id": 63302,
        "name": "Chikushino-shi",
        "country": "JPN",
        "state": "40"
    },
    {
        "id": 63325,
        "name": "Dazaifu-shi",
        "country": "JPN",
        "state": "40"
    },
    {
        "id": 63365,
        "name": "Fukuoka",
        "country": "JPN",
        "state": "40"
    },
    {
        "id": 63366,
        "name": "Fukuoka-shi",
        "country": "JPN",
        "state": "40"
    },
    {
        "id": 63372,
        "name": "Fukutsu Shi",
        "country": "JPN",
        "state": "40"
    },
    {
        "id": 63551,
        "name": "Iizuka",
        "country": "JPN",
        "state": "40"
    },
    {
        "id": 63552,
        "name": "Iizuka Shi",
        "country": "JPN",
        "state": "40"
    },
    {
        "id": 63614,
        "name": "Itoshima-shi",
        "country": "JPN",
        "state": "40"
    },
    {
        "id": 63676,
        "name": "Kama Shi",
        "country": "JPN",
        "state": "40"
    },
    {
        "id": 63708,
        "name": "Kanda",
        "country": "JPN",
        "state": "40"
    },
    {
        "id": 63744,
        "name": "Kasuga Shi",
        "country": "JPN",
        "state": "40"
    },
    {
        "id": 63776,
        "name": "Kawasaki",
        "country": "JPN",
        "state": "40"
    },
    {
        "id": 63808,
        "name": "Kitakyushu",
        "country": "JPN",
        "state": "40"
    },
    {
        "id": 63823,
        "name": "Koga",
        "country": "JPN",
        "state": "40"
    },
    {
        "id": 63825,
        "name": "Koga-shi",
        "country": "JPN",
        "state": "40"
    },
    {
        "id": 63879,
        "name": "Kurume",
        "country": "JPN",
        "state": "40"
    },
    {
        "id": 63880,
        "name": "Kurume Shi",
        "country": "JPN",
        "state": "40"
    },
    {
        "id": 63907,
        "name": "Maebaru-chūō",
        "country": "JPN",
        "state": "40"
    },
    {
        "id": 64005,
        "name": "Miyama Shi",
        "country": "JPN",
        "state": "40"
    },
    {
        "id": 64007,
        "name": "Miyata",
        "country": "JPN",
        "state": "40"
    },
    {
        "id": 64008,
        "name": "Miyawaka Shi",
        "country": "JPN",
        "state": "40"
    },
    {
        "id": 64044,
        "name": "Munakata-shi",
        "country": "JPN",
        "state": "40"
    },
    {
        "id": 64084,
        "name": "Nakama",
        "country": "JPN",
        "state": "40"
    },
    {
        "id": 64085,
        "name": "Nakama Shi",
        "country": "JPN",
        "state": "40"
    },
    {
        "id": 64147,
        "name": "Nishifukuma",
        "country": "JPN",
        "state": "40"
    },
    {
        "id": 64174,
        "name": "Nōgata",
        "country": "JPN",
        "state": "40"
    },
    {
        "id": 64175,
        "name": "Nōgata Shi",
        "country": "JPN",
        "state": "40"
    },
    {
        "id": 64189,
        "name": "Ogōri-shi",
        "country": "JPN",
        "state": "40"
    },
    {
        "id": 64730,
        "name": "Ōkawa",
        "country": "JPN",
        "state": "40"
    },
    {
        "id": 64731,
        "name": "Ōkawa-shi",
        "country": "JPN",
        "state": "40"
    },
    {
        "id": 64745,
        "name": "Ōmuta",
        "country": "JPN",
        "state": "40"
    },
    {
        "id": 64746,
        "name": "Ōmuta Shi",
        "country": "JPN",
        "state": "40"
    },
    {
        "id": 64207,
        "name": "Onga-gun",
        "country": "JPN",
        "state": "40"
    },
    {
        "id": 64749,
        "name": "Ōnojō",
        "country": "JPN",
        "state": "40"
    },
    {
        "id": 64750,
        "name": "Ōnojō Shi",
        "country": "JPN",
        "state": "40"
    },
    {
        "id": 64287,
        "name": "Sasaguri",
        "country": "JPN",
        "state": "40"
    },
    {
        "id": 64303,
        "name": "Setakamachi-takayanagi",
        "country": "JPN",
        "state": "40"
    },
    {
        "id": 64318,
        "name": "Shiida",
        "country": "JPN",
        "state": "40"
    },
    {
        "id": 64340,
        "name": "Shingū",
        "country": "JPN",
        "state": "40"
    },
    {
        "id": 64408,
        "name": "Tagawa",
        "country": "JPN",
        "state": "40"
    },
    {
        "id": 64409,
        "name": "Tagawa Shi",
        "country": "JPN",
        "state": "40"
    },
    {
        "id": 64468,
        "name": "Tanushimarumachi-toyoki",
        "country": "JPN",
        "state": "40"
    },
    {
        "id": 64543,
        "name": "Tsuiki",
        "country": "JPN",
        "state": "40"
    },
    {
        "id": 64588,
        "name": "Ukiha Shi",
        "country": "JPN",
        "state": "40"
    },
    {
        "id": 64589,
        "name": "Umi",
        "country": "JPN",
        "state": "40"
    },
    {
        "id": 64648,
        "name": "Yame Shi",
        "country": "JPN",
        "state": "40"
    },
    {
        "id": 64650,
        "name": "Yanagawa",
        "country": "JPN",
        "state": "40"
    },
    {
        "id": 64651,
        "name": "Yanagawa Shi",
        "country": "JPN",
        "state": "40"
    },
    {
        "id": 64689,
        "name": "Yoshitomi",
        "country": "JPN",
        "state": "40"
    },
    {
        "id": 64696,
        "name": "Yukuhashi",
        "country": "JPN",
        "state": "40"
    },
    {
        "id": 64697,
        "name": "Yukuhashi Shi",
        "country": "JPN",
        "state": "40"
    }
]