[
    {
        "id": 66739,
        "name": "Bissen",
        "country": "LUX",
        "state": "ME"
    },
    {
        "id": 66741,
        "name": "Boevange-sur-Attert",
        "country": "LUX",
        "state": "ME"
    },
    {
        "id": 66750,
        "name": "Colmar",
        "country": "LUX",
        "state": "ME"
    },
    {
        "id": 66770,
        "name": "Fischbach",
        "country": "LUX",
        "state": "ME"
    },
    {
        "id": 66779,
        "name": "Heffingen",
        "country": "LUX",
        "state": "ME"
    },
    {
        "id": 66796,
        "name": "Larochette",
        "country": "LUX",
        "state": "ME"
    },
    {
        "id": 66799,
        "name": "Lintgen",
        "country": "LUX",
        "state": "ME"
    },
    {
        "id": 66800,
        "name": "Lorentzweiler",
        "country": "LUX",
        "state": "ME"
    },
    {
        "id": 66805,
        "name": "Mersch",
        "country": "LUX",
        "state": "ME"
    },
    {
        "id": 66816,
        "name": "Nommern",
        "country": "LUX",
        "state": "ME"
    },
    {
        "id": 66830,
        "name": "Rollingen",
        "country": "LUX",
        "state": "ME"
    },
    {
        "id": 66850,
        "name": "Tuntange",
        "country": "LUX",
        "state": "ME"
    }
]