[
    {
        "id": 56338,
        "name": "Kabupaten Bantul",
        "country": "IDN",
        "state": "YO"
    },
    {
        "id": 56414,
        "name": "Kabupaten Gunung Kidul",
        "country": "IDN",
        "state": "YO"
    },
    {
        "id": 56473,
        "name": "Kabupaten Kulon Progo",
        "country": "IDN",
        "state": "YO"
    },
    {
        "id": 56637,
        "name": "Kabupaten Sleman",
        "country": "IDN",
        "state": "YO"
    },
    {
        "id": 57061,
        "name": "Yogyakarta",
        "country": "IDN",
        "state": "YO"
    }
]