[{"id":0,"name":"Aguanqueterique"},{"id":1,"name":"Caba\u00f1as"},{"id":2,"name":"Cane"},{"id":3,"name":"Chinacla"},{"id":4,"name":"Guajiquiro"},{"id":5,"name":"La Paz"},{"id":6,"name":"Lauterique"},{"id":7,"name":"Los Planes"},{"id":8,"name":"Marcala"},{"id":9,"name":"Mercedes de Oriente"},{"id":10,"name":"Opatoro"},{"id":11,"name":"San Antonio del Norte"},{"id":12,"name":"San Jos\u00e9"},{"id":13,"name":"San Juan"},{"id":14,"name":"San Pedro de Tutule"},{"id":15,"name":"Santa Ana"},{"id":16,"name":"Santa Elena"},{"id":17,"name":"Santa Mar\u00eda"},{"id":18,"name":"Santiago Puringla"},{"id":19,"name":"Tepanguare"},{"id":20,"name":"Yarula"},{"id":21,"name":"Yarumela"}]