[
    {
        "id": 135230,
        "name": "Ísafjarðarbær",
        "country": "ISL",
        "state": "4"
    },
    {
        "id": 135231,
        "name": "Ísafjörður",
        "country": "ISL",
        "state": "4"
    },
    {
        "id": 135204,
        "name": "Reykhólahreppur",
        "country": "ISL",
        "state": "4"
    },
    {
        "id": 135219,
        "name": "Strandabyggð",
        "country": "ISL",
        "state": "4"
    },
    {
        "id": 135224,
        "name": "Tálknafjarðarhreppur",
        "country": "ISL",
        "state": "4"
    }
]