[
    {
        "id": 52217,
        "name": "Abuko",
        "country": "GMB",
        "state": "W"
    },
    {
        "id": 52227,
        "name": "Brikama",
        "country": "GMB",
        "state": "W"
    },
    {
        "id": 52241,
        "name": "Foni Bondali",
        "country": "GMB",
        "state": "W"
    },
    {
        "id": 52242,
        "name": "Foni Brefet",
        "country": "GMB",
        "state": "W"
    },
    {
        "id": 52243,
        "name": "Foni Jarrol",
        "country": "GMB",
        "state": "W"
    },
    {
        "id": 52244,
        "name": "Foni Kansala",
        "country": "GMB",
        "state": "W"
    },
    {
        "id": 52249,
        "name": "Gunjur",
        "country": "GMB",
        "state": "W"
    },
    {
        "id": 52274,
        "name": "Kombo Central District",
        "country": "GMB",
        "state": "W"
    },
    {
        "id": 52275,
        "name": "Kombo East District",
        "country": "GMB",
        "state": "W"
    },
    {
        "id": 52276,
        "name": "Kombo North District",
        "country": "GMB",
        "state": "W"
    },
    {
        "id": 52278,
        "name": "Kombo South District",
        "country": "GMB",
        "state": "W"
    },
    {
        "id": 52307,
        "name": "Somita",
        "country": "GMB",
        "state": "W"
    },
    {
        "id": 52310,
        "name": "Sukuta",
        "country": "GMB",
        "state": "W"
    }
]