[{"id":0,"name":"Chicacao"},{"id":1,"name":"Cuyotenango"},{"id":2,"name":"Mazatenango"},{"id":3,"name":"Municipio de San Antonio Suchitep\u00e9quez"},{"id":4,"name":"Municipio de San Miguel Pan\u00e1n"},{"id":5,"name":"Municipio de Santa B\u00e1rbara"},{"id":6,"name":"Patulul"},{"id":7,"name":"Pueblo Nuevo"},{"id":8,"name":"R\u00edo Bravo"},{"id":9,"name":"San Antonio Suchitep\u00e9quez"},{"id":10,"name":"San Bernardino"},{"id":11,"name":"San Francisco Zapotitl\u00e1n"},{"id":12,"name":"San Gabriel"},{"id":13,"name":"San Jos\u00e9 El \u00cddolo"},{"id":14,"name":"San Juan Bautista"},{"id":15,"name":"San Lorenzo"},{"id":16,"name":"San Miguel Pan\u00e1n"},{"id":17,"name":"San Pablo Jocopilas"},{"id":18,"name":"Santa B\u00e1rbara"},{"id":19,"name":"Santo Domingo Suchitep\u00e9quez"},{"id":20,"name":"Santo Tom\u00e1s La Uni\u00f3n"},{"id":21,"name":"Zunilito"}]