[{"id":0,"name":"Aichi Prefecture","iso3":"23"},{"id":1,"name":"Akita Prefecture","iso3":"05"},{"id":2,"name":"Aomori Prefecture","iso3":"02"},{"id":3,"name":"Chiba Prefecture","iso3":"12"},{"id":4,"name":"Ehime Prefecture","iso3":"38"},{"id":5,"name":"Fukui Prefecture","iso3":"18"},{"id":6,"name":"Fukuoka Prefecture","iso3":"40"},{"id":7,"name":"Fukushima Prefecture","iso3":"07"},{"id":8,"name":"Gifu Prefecture","iso3":"21"},{"id":9,"name":"Gunma Prefecture","iso3":"10"},{"id":10,"name":"Hiroshima Prefecture","iso3":"34"},{"id":11,"name":"Hokkaid\u014d Prefecture","iso3":"01"},{"id":12,"name":"Hy\u014dgo Prefecture","iso3":"28"},{"id":13,"name":"Ibaraki Prefecture","iso3":"08"},{"id":14,"name":"Ishikawa Prefecture","iso3":"17"},{"id":15,"name":"Iwate Prefecture","iso3":"03"},{"id":16,"name":"Kagawa Prefecture","iso3":"37"},{"id":17,"name":"Kagoshima Prefecture","iso3":"46"},{"id":18,"name":"Kanagawa Prefecture","iso3":"14"},{"id":19,"name":"K\u014dchi Prefecture","iso3":"39"},{"id":20,"name":"Kumamoto Prefecture","iso3":"43"},{"id":21,"name":"Ky\u014dto Prefecture","iso3":"26"},{"id":22,"name":"Mie Prefecture","iso3":"24"},{"id":23,"name":"Miyagi Prefecture","iso3":"04"},{"id":24,"name":"Miyazaki Prefecture","iso3":"45"},{"id":25,"name":"Nagano Prefecture","iso3":"20"},{"id":26,"name":"Nagasaki Prefecture","iso3":"42"},{"id":27,"name":"Nara Prefecture","iso3":"29"},{"id":28,"name":"Niigata Prefecture","iso3":"15"},{"id":29,"name":"\u014cita Prefecture","iso3":"44"},{"id":30,"name":"Okayama Prefecture","iso3":"33"},{"id":31,"name":"Okinawa Prefecture","iso3":"47"},{"id":32,"name":"\u014csaka Prefecture","iso3":"27"},{"id":33,"name":"Saga Prefecture","iso3":"41"},{"id":34,"name":"Saitama Prefecture","iso3":"11"},{"id":35,"name":"Shiga Prefecture","iso3":"25"},{"id":36,"name":"Shimane Prefecture","iso3":"32"},{"id":37,"name":"Shizuoka Prefecture","iso3":"22"},{"id":38,"name":"Tochigi Prefecture","iso3":"09"},{"id":39,"name":"Tokushima Prefecture","iso3":"36"},{"id":40,"name":"Tokyo","iso3":"13"},{"id":41,"name":"Tottori Prefecture","iso3":"31"},{"id":42,"name":"Toyama Prefecture","iso3":"16"},{"id":43,"name":"Wakayama Prefecture","iso3":"30"},{"id":44,"name":"Yamagata Prefecture","iso3":"06"},{"id":45,"name":"Yamaguchi Prefecture","iso3":"35"},{"id":46,"name":"Yamanashi Prefecture","iso3":"19"}]