[
    {
        "id": 150710,
        "name": "Abgarm",
        "country": "IRN",
        "state": "26"
    },
    {
        "id": 150708,
        "name": "Abyek",
        "country": "IRN",
        "state": "26"
    },
    {
        "id": 134563,
        "name": "Alborz",
        "country": "IRN",
        "state": "26"
    },
    {
        "id": 134565,
        "name": "Alvand",
        "country": "IRN",
        "state": "26"
    },
    {
        "id": 150714,
        "name": "Ardagh",
        "country": "IRN",
        "state": "26"
    },
    {
        "id": 134572,
        "name": "Avaj",
        "country": "IRN",
        "state": "26"
    },
    {
        "id": 150711,
        "name": "Bidestan",
        "country": "IRN",
        "state": "26"
    },
    {
        "id": 134831,
        "name": "Buin Zahra",
        "country": "IRN",
        "state": "26"
    },
    {
        "id": 150715,
        "name": "Danesfahan",
        "country": "IRN",
        "state": "26"
    },
    {
        "id": 150722,
        "name": "Eqbaliyeh",
        "country": "IRN",
        "state": "26"
    },
    {
        "id": 150718,
        "name": "Esfarvarin",
        "country": "IRN",
        "state": "26"
    },
    {
        "id": 150709,
        "name": "Khakali",
        "country": "IRN",
        "state": "26"
    },
    {
        "id": 150719,
        "name": "Khorramdasht",
        "country": "IRN",
        "state": "26"
    },
    {
        "id": 150725,
        "name": "Kouhin",
        "country": "IRN",
        "state": "26"
    },
    {
        "id": 150726,
        "name": "Mahmood Abad nemooneh",
        "country": "IRN",
        "state": "26"
    },
    {
        "id": 150727,
        "name": "Moallem Kelayeh",
        "country": "IRN",
        "state": "26"
    },
    {
        "id": 150713,
        "name": "Mohammadiyeh ",
        "country": "IRN",
        "state": "26"
    },
    {
        "id": 150721,
        "name": "Narjeh",
        "country": "IRN",
        "state": "26"
    },
    {
        "id": 134740,
        "name": "Qazvin",
        "country": "IRN",
        "state": "26"
    },
    {
        "id": 150723,
        "name": "Razmian",
        "country": "IRN",
        "state": "26"
    },
    {
        "id": 150716,
        "name": "Sagz Abad",
        "country": "IRN",
        "state": "26"
    },
    {
        "id": 150717,
        "name": "Shal",
        "country": "IRN",
        "state": "26"
    },
    {
        "id": 150712,
        "name": "Sharif Abad",
        "country": "IRN",
        "state": "26"
    },
    {
        "id": 150724,
        "name": "Sirdan",
        "country": "IRN",
        "state": "26"
    },
    {
        "id": 135134,
        "name": "Takestan",
        "country": "IRN",
        "state": "26"
    },
    {
        "id": 150720,
        "name": "Ziaabad",
        "country": "IRN",
        "state": "26"
    }
]