[
    {
        "id": 109331,
        "name": "Askaniya-Nova",
        "country": "UKR",
        "state": "65"
    },
    {
        "id": 109361,
        "name": "Bekhtery",
        "country": "UKR",
        "state": "65"
    },
    {
        "id": 109388,
        "name": "Beryslav",
        "country": "UKR",
        "state": "65"
    },
    {
        "id": 109404,
        "name": "Bilozerka",
        "country": "UKR",
        "state": "65"
    },
    {
        "id": 109454,
        "name": "Brylivka",
        "country": "UKR",
        "state": "65"
    },
    {
        "id": 109472,
        "name": "Chaplynka",
        "country": "UKR",
        "state": "65"
    },
    {
        "id": 109511,
        "name": "Chornobayivka",
        "country": "UKR",
        "state": "65"
    },
    {
        "id": 109516,
        "name": "Chornyanka",
        "country": "UKR",
        "state": "65"
    },
    {
        "id": 109523,
        "name": "Chulakivka",
        "country": "UKR",
        "state": "65"
    },
    {
        "id": 109554,
        "name": "Dnipryany",
        "country": "UKR",
        "state": "65"
    },
    {
        "id": 109587,
        "name": "Dudchany",
        "country": "UKR",
        "state": "65"
    },
    {
        "id": 109628,
        "name": "Heniches’k",
        "country": "UKR",
        "state": "65"
    },
    {
        "id": 109629,
        "name": "Heniches’kyy Rayon",
        "country": "UKR",
        "state": "65"
    },
    {
        "id": 109636,
        "name": "Hola Prystan’",
        "country": "UKR",
        "state": "65"
    },
    {
        "id": 109642,
        "name": "Hornostayivka",
        "country": "UKR",
        "state": "65"
    },
    {
        "id": 109679,
        "name": "Ivanivka",
        "country": "UKR",
        "state": "65"
    },
    {
        "id": 109697,
        "name": "Kakhovka",
        "country": "UKR",
        "state": "65"
    },
    {
        "id": 109698,
        "name": "Kalanchak",
        "country": "UKR",
        "state": "65"
    },
    {
        "id": 109722,
        "name": "Kayiry",
        "country": "UKR",
        "state": "65"
    },
    {
        "id": 109729,
        "name": "Kherson",
        "country": "UKR",
        "state": "65"
    },
    {
        "id": 109786,
        "name": "Komyshany",
        "country": "UKR",
        "state": "65"
    },
    {
        "id": 109823,
        "name": "Kozachi Laheri",
        "country": "UKR",
        "state": "65"
    },
    {
        "id": 109833,
        "name": "Krasne",
        "country": "UKR",
        "state": "65"
    },
    {
        "id": 109907,
        "name": "Lazurne",
        "country": "UKR",
        "state": "65"
    },
    {
        "id": 109967,
        "name": "Lyubymivka",
        "country": "UKR",
        "state": "65"
    },
    {
        "id": 109983,
        "name": "Malokakhovka",
        "country": "UKR",
        "state": "65"
    },
    {
        "id": 110104,
        "name": "Nova Kakhovka",
        "country": "UKR",
        "state": "65"
    },
    {
        "id": 110105,
        "name": "Nova Mayachka",
        "country": "UKR",
        "state": "65"
    },
    {
        "id": 110125,
        "name": "Novofedorivka",
        "country": "UKR",
        "state": "65"
    },
    {
        "id": 110137,
        "name": "Novooleksiyivka",
        "country": "UKR",
        "state": "65"
    },
    {
        "id": 110153,
        "name": "Novovorontsovka",
        "country": "UKR",
        "state": "65"
    },
    {
        "id": 110165,
        "name": "Nyzhni Sirohozy",
        "country": "UKR",
        "state": "65"
    },
    {
        "id": 110227,
        "name": "Partyzany",
        "country": "UKR",
        "state": "65"
    },
    {
        "id": 110336,
        "name": "Radens’k",
        "country": "UKR",
        "state": "65"
    },
    {
        "id": 110466,
        "name": "Skadovs’k",
        "country": "UKR",
        "state": "65"
    },
    {
        "id": 110525,
        "name": "Stanislav",
        "country": "UKR",
        "state": "65"
    },
    {
        "id": 110634,
        "name": "Tsyurupyns’k",
        "country": "UKR",
        "state": "65"
    },
    {
        "id": 110685,
        "name": "Velyka Lepetykha",
        "country": "UKR",
        "state": "65"
    },
    {
        "id": 110687,
        "name": "Velyka Oleksandrivka",
        "country": "UKR",
        "state": "65"
    },
    {
        "id": 110690,
        "name": "Velyki Kopani",
        "country": "UKR",
        "state": "65"
    },
    {
        "id": 110706,
        "name": "Verkhniy Rohachyk",
        "country": "UKR",
        "state": "65"
    },
    {
        "id": 110760,
        "name": "Vynohradove",
        "country": "UKR",
        "state": "65"
    },
    {
        "id": 110767,
        "name": "Vysokopillya",
        "country": "UKR",
        "state": "65"
    },
    {
        "id": 110817,
        "name": "Zaliznyy Port",
        "country": "UKR",
        "state": "65"
    }
]