[{"id":0,"name":"Changnyeong"},{"id":1,"name":"Changnyeong-gun"},{"id":2,"name":"Changwon"},{"id":3,"name":"Changwon-si"},{"id":4,"name":"Chinju"},{"id":5,"name":"Geochang-gun"},{"id":6,"name":"Geoje-si"},{"id":7,"name":"Gimhae-si"},{"id":8,"name":"Goseong"},{"id":9,"name":"Goseong-gun"},{"id":10,"name":"Hadong-gun"},{"id":11,"name":"Haman-gun"},{"id":12,"name":"Hapcheon-gun"},{"id":13,"name":"Jinju-si"},{"id":14,"name":"Kimhae"},{"id":15,"name":"Kyosai"},{"id":16,"name":"Miryang"},{"id":17,"name":"Miryang-si"},{"id":18,"name":"Naes\u014f"},{"id":19,"name":"Namhae-gun"},{"id":20,"name":"Sacheon-si"},{"id":21,"name":"Sancheong-gun"},{"id":22,"name":"Sinhyeon"},{"id":23,"name":"Uiryeong-gun"},{"id":24,"name":"Ungsang"},{"id":25,"name":"Yangsan"}]