[
    {
        "id": 76744,
        "name": "Aba",
        "country": "NGA",
        "state": "AB"
    },
    {
        "id": 76769,
        "name": "Amaigbo",
        "country": "NGA",
        "state": "AB"
    },
    {
        "id": 76779,
        "name": "Arochukwu",
        "country": "NGA",
        "state": "AB"
    },
    {
        "id": 76799,
        "name": "Bende",
        "country": "NGA",
        "state": "AB"
    },
    {
        "id": 77057,
        "name": "Ohafia-Ifigh",
        "country": "NGA",
        "state": "AB"
    },
    {
        "id": 77125,
        "name": "Umuahia",
        "country": "NGA",
        "state": "AB"
    }
]