[{"id":0,"name":"Aheloy","country_iso3":"BGR","state_iso3":"02"},{"id":1,"name":"Ahtopol","country_iso3":"BGR","state_iso3":"02"},{"id":2,"name":"Aytos","country_iso3":"BGR","state_iso3":"02"},{"id":3,"name":"Bata","country_iso3":"BGR","state_iso3":"02"},{"id":4,"name":"Burgas","country_iso3":"BGR","state_iso3":"02"},{"id":5,"name":"Chernomorets","country_iso3":"BGR","state_iso3":"02"},{"id":6,"name":"Kameno","country_iso3":"BGR","state_iso3":"02"},{"id":7,"name":"Karnobat","country_iso3":"BGR","state_iso3":"02"},{"id":8,"name":"Kiten","country_iso3":"BGR","state_iso3":"02"},{"id":9,"name":"Malko Tarnovo","country_iso3":"BGR","state_iso3":"02"},{"id":10,"name":"Nesebar","country_iso3":"BGR","state_iso3":"02"},{"id":11,"name":"Obshtina Aytos","country_iso3":"BGR","state_iso3":"02"},{"id":12,"name":"Obshtina Burgas","country_iso3":"BGR","state_iso3":"02"},{"id":13,"name":"Obshtina Kameno","country_iso3":"BGR","state_iso3":"02"},{"id":14,"name":"Obshtina Karnobat","country_iso3":"BGR","state_iso3":"02"},{"id":15,"name":"Obshtina Malko Tarnovo","country_iso3":"BGR","state_iso3":"02"},{"id":16,"name":"Obshtina Nesebar","country_iso3":"BGR","state_iso3":"02"},{"id":17,"name":"Obshtina Pomorie","country_iso3":"BGR","state_iso3":"02"},{"id":18,"name":"Obshtina Primorsko","country_iso3":"BGR","state_iso3":"02"},{"id":19,"name":"Obshtina Sozopol","country_iso3":"BGR","state_iso3":"02"},{"id":20,"name":"Obshtina Sungurlare","country_iso3":"BGR","state_iso3":"02"},{"id":21,"name":"Obzor","country_iso3":"BGR","state_iso3":"02"},{"id":22,"name":"Pomorie","country_iso3":"BGR","state_iso3":"02"},{"id":23,"name":"Primorsko","country_iso3":"BGR","state_iso3":"02"},{"id":24,"name":"Ravda","country_iso3":"BGR","state_iso3":"02"},{"id":25,"name":"Ruen","country_iso3":"BGR","state_iso3":"02"},{"id":26,"name":"Sarafovo","country_iso3":"BGR","state_iso3":"02"},{"id":27,"name":"Sozopol","country_iso3":"BGR","state_iso3":"02"},{"id":28,"name":"Sredets","country_iso3":"BGR","state_iso3":"02"},{"id":29,"name":"Sungurlare","country_iso3":"BGR","state_iso3":"02"},{"id":30,"name":"Sveti Vlas","country_iso3":"BGR","state_iso3":"02"},{"id":31,"name":"Tsarevo","country_iso3":"BGR","state_iso3":"02"}]